rokuecp/__init__.py
rokuecp/const.py
rokuecp/exceptions.py
rokuecp/helpers.py
rokuecp/models.py
rokuecp/py.typed
rokuecp/resolver.py
rokuecp/rokuecp.py
rokuecp-0.19.5.dist-info/LICENSE
rokuecp-0.19.5.dist-info/METADATA
rokuecp-0.19.5.dist-info/WHEEL
rokuecp-0.19.5.dist-info/RECORD
